LICENSE.txt
README.txt
setup.py
src/cornerstone/__init__.py
src/cornerstone.cssvar.egg-info/PKG-INFO
src/cornerstone.cssvar.egg-info/SOURCES.txt
src/cornerstone.cssvar.egg-info/dependency_links.txt
src/cornerstone.cssvar.egg-info/namespace_packages.txt
src/cornerstone.cssvar.egg-info/not-zip-safe
src/cornerstone.cssvar.egg-info/requires.txt
src/cornerstone.cssvar.egg-info/top_level.txt
src/cornerstone/cssvar/__init__.py
src/cornerstone/cssvar/browser.py
src/cornerstone/cssvar/five.py
src/cornerstone/cssvar/interfaces.py
src/cornerstone/cssvar/meta.py
src/cornerstone/cssvar/meta.zcml
src/cornerstone/cssvar/resource.py