Metadata-Version: 1.0
Name: cornerstone.cssvar
Version: 1.0
Summary: CSS Variables Support for Zope.
Home-page: UNKNOWN
Author: Jens Klein
Author-email: jens@bluedynamics.com
License: BSD License derivative
Keywords: css variables resource
Platform: UNKNOWN
Classifier: License :: OSI Approved :: BSD License
Classifier: Operating System :: OS Independent
Classifier: Programming Language :: Python
Classifier: Framework :: Zope3
Classifier: Environment :: Web Environment
